<?xml version="1.0" encoding="UTF-8" standalone="no"?>
<partitionInfo version="1.0" library="LPRES_EXAMPLES_2" component="Turbine_performance" partition="OffDesign">
<noDerivatives value="FALSE"/>
<inhibitReductionConstantCoefEqts value="FALSE"/>
<generatePartitionClass value="FALSE"/>
<removeNotUsedVars value="FALSE"/>
<showPropertyPanel value="FALSE"/>
<generateProtectedMathFunctions value="TRUE"/>
<generatePerformanceMeters value="FALSE"/>
<generateObfuscatedCpp value="FALSE"/>
<generateParInfoHTML value="TRUE"/>
<generateMaxSignificantDigits value="FALSE"/>
<noDatas>
  <variable name="Nozzle_1.A"/>
</noDatas>
<boundaries>
  <variable name="Inlet_1.Tt"/>
  <variable name="Inlet_1.pt"/>
  <variable name="LPRES.Altitude"/>
  <variable name="Nozzle_1.A"/>
  <variable name="Turbine_1.m.N"/>
</boundaries>
<algebraics>
  <variable name="Turbine_1.M_2"/>
</algebraics>
</partitionInfo>
